endorlabs_atst/__init__.py
endorlabs_atst/__main__.py
endorlabs_atst/cmd_check_regex.py
endorlabs_atst/cmd_ctl.py
endorlabs_atst/cmd_setup.py
endorlabs_atst/main.py
endorlabs_atst/utils/__init__.py
endorlabs_atst/utils/ci_detection.py
endorlabs_atst/utils/commandstreamer.py
endorlabs_atst/utils/osarch.py
endorlabs_atst/utils/statuswriter.py
endorlabs_atst/utils/verdata.py
endorlabs_atst-0.4.1.dist-info/METADATA
endorlabs_atst-0.4.1.dist-info/WHEEL
endorlabs_atst-0.4.1.dist-info/entry_points.txt
endorlabs_atst-0.4.1.dist-info/top_level.txt
endorlabs_atst-0.4.1.dist-info/RECORD
