Metadata-Version: 2.1
Name: endorlabs-atst
Version: 0.4.1
Summary: Endor Labs Automated Tool for Scanning Things (ATST) -- a tool to help deploy and manage Endor Labs in CI pipelines
Author-email: Darren Meyer <darren@endor.ai>
Project-URL: homepage, https://github.com/endorlabs/atst
Requires-Python: >=3.9
Requires-Dist: click ~=8.1
Requires-Dist: requests ~=2.31
Requires-Dist: semantic-version ~=2.10
Requires-Dist: google-re2 ~=1.1
Provides-Extra: test
Requires-Dist: pytest ~=7.4 ; extra == 'test'
